Stockie/Candlestick.py
Stockie/__init__.py
Stockie/pattern_img.json
Stockie/pattern_type.json
Stockie/report.py
Stockie/stockie.py
stockie-1.0.25.dist-info/METADATA
stockie-1.0.25.dist-info/WHEEL
stockie-1.0.25.dist-info/top_level.txt
stockie-1.0.25.dist-info/RECORD
