Metadata-Version: 2.1
Name: stockie
Version: 1.0.25
Summary: A package to identify stock candlestick pattern
Home-page: https://github.com/suparjotamin/stockie
Author: Suparjo Tamin
Author-email: suparjo.tamin@gmail.com
License: UNKNOWN
Platform: UNKNOWN
Classifier: Programming Language :: Python :: 3
Classifier: License :: OSI Approved :: MIT License
Classifier: Operating System :: OS Independent
Requires-Python: >=3.6
Requires-Dist: yfinance
Requires-Dist: mpl-finance
